[
  {
    "prod_HRTGHbm4A02KE1": {
      "description": "1 Bottle Shiaqga Super Concentrate",
      "caption": "1 Bottle Shiaqga Super Concentrate",
      "shippable": true
    }
  },
  {
    "prod_HRTGJcdbfcQkab": {
      "description": "2 Bottles Shiaqga Super Concentrate",
      "caption": "2 Bottles Shiaqga Super Concentrate",
      "shippable": true
    }
  },
  {
    "prod_HRTGWqO3Cy8jaD": {
      "description": "4 Bottles Shiaqga Super Concentrate",
      "caption": "4 Bottles Shiaqga Super Concentrate",
      "shippable": true
    }
  },
  {
    "prod_HRTGtLKX0WePdz": {
      "description": "6 Bottles Shiaqga Super Concentrate",
      "caption": "6 Bottles Shiaqga Super Concentrate",
      "shippable": true
    }
  },
  {
    "prod_HRTGibtCNKVOIr": {
      "description": "12 Bottles Shiaqga Super Concentrate",
      "caption": "12 Bottles Shiaqga Super Concentrate",
      "shippable": true
    }
  }
]
